tune_jax/__init__.py
tune_jax/tuning.py
tune_jax/experimental/record.py
tune_jax/profile_reader/__init__.py
tune_jax/profile_reader/old_parse_profile.py
tune_jax/profile_reader/parse_profile.py
tune_jax/profile_reader/xplane_pb2.py
tune_jax-0.6.1.dist-info/licenses/LICENSE
tune_jax-0.6.1.dist-info/METADATA
tune_jax-0.6.1.dist-info/WHEEL
tune_jax-0.6.1.dist-info/top_level.txt
tune_jax-0.6.1.dist-info/RECORD
