Metadata-Version: 2.4
Name: tune_jax
Version: 0.6.1
Summary: Microbenchmarking hyperparameter tuning for JAX functions.
Author: Robert Dyro
License: Copyright (c) 2024 Robert Dyro
License-File: LICENSE
Requires-Dist: jax
Requires-Dist: numpy
Requires-Dist: tqdm
Requires-Dist: protobuf
Requires-Dist: tabulate
Provides-Extra: test
Requires-Dist: absl-py; extra == "test"
Requires-Dist: pytest; extra == "test"
Dynamic: license-file
